tasks_prompts_chain/__init__.py
tasks_prompts_chain/client_llm_sdk.py
tasks_prompts_chain/tasks_prompts_chain.py
tasks_prompts_chain-0.1.2.dist-info/METADATA
tasks_prompts_chain-0.1.2.dist-info/WHEEL
tasks_prompts_chain-0.1.2.dist-info/licenses/LICENSE
tasks_prompts_chain-0.1.2.dist-info/RECORD
