Metadata-Version: 2.4
Name: tasks_prompts_chain
Version: 0.1.2
Summary: A Python library for creating and executing chains of prompts using multiple LLM providers with streaming support and template formatting.
Project-URL: Homepage, https://github.com/smirfolio/tasks_prompts_chain
Project-URL: Issues, https://github.com/smirfolio/tasks_prompts_chain/issues
Author-email: Samir Ben Sghaier <ben.sghaier.samir@gmail.com>
License-Expression: Apache-2.0
License-File: LICENSE
Classifier: Operating System :: OS Independent
Classifier: Programming Language :: Python :: 3
Requires-Python: >=3.8
